Workbook
Name aporte: Simulador!$D$12
Name patrimonio: Simulador!$D$15
Name qtd_anos: Simulador!$D$13
Name rendimento_carteira: Simulador!$D$8
Name salario: Simulador!$D$7
Name taxa_mensal: Simulador!$D$14

Sheet Simulador
B6: CONFIGURAÇÕES
B7: Salário | D7: 8500
B8: Rendimento Carteira | D8: 0.006
B9: Sugestão de Investimento (30%) | D9: =D7*30% -> 2550
B11: INVESTIMENTO MENSAL
B12: Quanto investir por mês ? | D12: 4000
B13: Por Quantos Anos ? | D13: 5
B14: Taxa de Rendimento mensal ? | D14: 0.0108
B15: Patrimônio acumulado ? | D15: =FV(taxa_mensal,qtd_anos*12,aporte*-1) -> 335216.08
B16: Dividendos Mensais ? | D16: =patrimonio*rendimento_carteira -> 2011.2965
B18: CENÁRIOS PROVÁVEIS | D18: Dividendo
A19: 2 | B19: Quanto em 2 Anos ? | C19: =FV($D$14,$A19*12,$D$12*-1) -> 108923.45 | D19: =C19*rendimento_carteira -> 653.54073
A20: 5 | B20: Quanto em 5 Anos ? | C20: =FV($D$14,$A20*12,$D$12*-1) -> 335216.08 | D20: =C20*rendimento_carteira -> 2011.2965
A21: 10 | B21: Quanto em 10 Anos ? | C21: =FV($D$14,$A21*12,$D$12*-1) -> 973830.67 | D21: =C21*rendimento_carteira -> 5842.984
A22: 20 | B22: Quanto em 20 Anos ? | C22: =FV($D$14,$A22*12,$D$12*-1) -> 4508196 | D22: =C22*rendimento_carteira -> 27049.176
A23: 30 | B23: Quanto em 30 Anos ? | C23: =FV($D$14,$A23*12,$D$12*-1) -> 17335619 | D23: =C23*rendimento_carteira -> 104013.72
A25: * Rendimentos passados não asseguram o mesmo rendimento em momento futuro
B28: DISTRIBUIÇÃO
B30: PERFIL | C30: Agressivo
B32: VALOR A SER INVESTIDO POR MÊS | C32: =D12 -> 4000
B34: TIPO DE FII | C34: Percentual Sugerido | D34: Valores
B35: PAPEL | C35: =VLOOKUP($C$30&"-"&B35,Base!$A:$D,4,FALSE) -> 0.5 | D35: =C35*$C$32 -> 2000
B36: TIJOLO | C36: =VLOOKUP($C$30&"-"&B36,Base!$A:$D,4,FALSE) -> 0.1 | D36: =C36*$C$32 -> 400
B37: HÍBRIDOS | C37: =VLOOKUP($C$30&"-"&B37,Base!$A:$D,4,FALSE) -> 0.05 | D37: =C37*$C$32 -> 200
B38: FOFs | C38: =VLOOKUP($C$30&"-"&B38,Base!$A:$D,4,FALSE) -> 0.05 | D38: =C38*$C$32 -> 200
B39: DESENVOLVIMENTO | C39: =VLOOKUP($C$30&"-"&B39,Base!$A:$D,4,FALSE) -> 0.2 | D39: =C39*$C$32 -> 800
B40: HOTELARIAS | C40: =VLOOKUP($C$30&"-"&B40,Base!$A:$D,4,FALSE) -> 0.1 | D40: =C40*$C$32 -> 400
D41: =SUM(D35:D40) -> 4000

Sheet Base
A2: CHAVE | B2: PERFIL | C2: TIPO DE FII | D2: %
A3: =B3&"-"&C3 -> Conservador-PAPEL | B3: Conservador | C3: PAPEL | D3: 0.3 | I3: %
A4: =B4&"-"&C4 -> Conservador-TIJOLO | B4: Conservador | C4: TIJOLO | D4: 0.5 | G4: Moderado-TIJOLO | H4: =VLOOKUP(A10,$A:$D,4,FALSE) -> 0.35
A5: =B5&"-"&C5 -> Conservador-HÍBRIDOS | B5: Conservador | C5: HÍBRIDOS | D5: 0.1
A6: =B6&"-"&C6 -> Conservador-FOFs | B6: Conservador | C6: FOFs | D6: 0.1
A7: =B7&"-"&C7 -> Conservador-DESENVOLVIMENTO | B7: Conservador | C7: DESENVOLVIMENTO | D7: 0
A8: =B8&"-"&C8 -> Conservador-HOTELARIAS | B8: Conservador | C8: HOTELARIAS | D8: 0
A9: =B9&"-"&C9 -> Moderado-PAPEL | B9: Moderado | C9: PAPEL | D9: 0.32
A10: =B10&"-"&C10 -> Moderado-TIJOLO | B10: Moderado | C10: TIJOLO | D10: 0.35
A11: =B11&"-"&C11 -> Moderado-HÍBRIDOS | B11: Moderado | C11: HÍBRIDOS | D11: 0.08
A12: =B12&"-"&C12 -> Moderado-FOFs | B12: Moderado | C12: FOFs | D12: 0.05
A13: =B13&"-"&C13 -> Moderado-DESENVOLVIMENTO | B13: Moderado | C13: DESENVOLVIMENTO | D13: 0.1
A14: =B14&"-"&C14 -> Moderado-HOTELARIAS | B14: Moderado | C14: HOTELARIAS | D14: 0.1
A15: =B15&"-"&C15 -> Agressivo-PAPEL | B15: Agressivo | C15: PAPEL | D15: 0.5
A16: =B16&"-"&C16 -> Agressivo-TIJOLO | B16: Agressivo | C16: TIJOLO | D16: 0.1
... A20: =B20&"-"&C20 -> Agressivo-HOTELARIAS | B20: Agressivo | C20: HOTELARIAS | D20: 0.1
